provstore
