Metadata-Version: 1.0
Name: provstore-api
Version: 0.1.2
Summary: ProvStore API client
Home-page: https://github.com/millar/provstore-api
Author: Sam Millar
Author-email: sam@millar.io
License: MIT
Platform: UNKNOWN
